setup.cfg
setup.py
MethylPurify.egg-info/PKG-INFO
MethylPurify.egg-info/SOURCES.txt
MethylPurify.egg-info/dependency_links.txt
MethylPurify.egg-info/requires.txt
MethylPurify.egg-info/top_level.txt
methylpurify/__init__.py
methylpurify/bin/MethylPurify
methylpurify/db/Amplification_from_TCGA_all_cancer.txt
methylpurify/db/CGI_hg18_slop1000.bed
methylpurify/db/CGI_hg19_slop1000.bed
methylpurify/db/Delitions_from_TCGA_all_cancer.txt