Metadata-Version: 1.0
Name: MethylPurify
Version: 2.0-20140310
Summary: Methylation subclone detection
Home-page: UNKNOWN
Author: Xiaoqi Zheng
Author-email: zheng.shnu@gmail.com
License: UNKNOWN
Keywords: genomics methylation
Platform: UNKNOWN
Classifier: Development Status :: 4 - Beta
Classifier: Environment :: Console
Classifier: Intended Audience :: Science/Research
Classifier: License :: OSI Approved :: Python Software Foundation License
Classifier: Operating System :: MacOS :: MacOS X
Classifier: Operating System :: POSIX :: Linux
Classifier: Operating System :: Unix
Classifier: Operating System :: POSIX
Classifier: Programming Language :: Python :: 2.6
Classifier: Programming Language :: Python :: 2.7
